account/__init__.py
account/account.ini
account/account.py
app/__init__.py
app/app.ini
app/app.py
ctl/__init__.py
ctl/constants.py
ctl/error.py
ctl/interactive_cli.py
ctl/list.py
ctl/logging_config.py
ctl/response_handle.py
ctl/server_config.ini
ctl/terminal.py
ctl/test.py
dashboard/__init__.py
dashboard/dashboard.ini
dashboard/dashboard.py
file_config/__init__.py
file_config/file.ini
file_config/space.py
file_config/test.py
file_config/upload.py
term/__init__.py
term/term.ini
term/term.py
skyctl-1.1.25.dist-info/METADATA
skyctl-1.1.25.dist-info/WHEEL
skyctl-1.1.25.dist-info/entry_points.txt
skyctl-1.1.25.dist-info/license.txt
skyctl-1.1.25.dist-info/top_level.txt
skyctl-1.1.25.dist-info/RECORD
