Metadata-Version: 2.1
Name: skyctl
Version: 1.1.25
Summary: SkyCtl CLI Tool For Skybackend Server
Author: XieJunWei
Author-email: 643657447@qq.com
License: MIT
Requires-Python: >=3
License-File: license.txt
Requires-Dist: pypinyin
Requires-Dist: opencv-python
Requires-Dist: requests
Requires-Dist: configparser
Requires-Dist: Click
Requires-Dist: tabulate
Requires-Dist: kubernetes
Requires-Dist: pyyaml
